{"inkVersion":21,"root":[["^Warrior:Oi, robes come over here! You have any idea what's going on!!","\n","ev","str","^No idea.","/str","/ev",{"*":"0.c-0","flg":4},{"c-0":["\n","^Warrior:The hell you mean no! Aren't you some type of magi!!!!","\n",{"->":"intro"},{"->":"0.g-0"},{"#f":5}],"g-0":["done",{"#f":5}]}],"done",{"intro":[["ev",{"CNT?":"name"},"/ev",[{"->":".^.b","c":true},{"b":["^ Heldar",{"->":".^.^.^.5"},null]}],[{"->":".^.b"},{"b":["^Warrior",{"->":".^.^.^.5"},null]}],"nop","^:If you have any idea then speak!","\n","ev","str","^What is your name warrior?","/str","/ev",{"*":".^.c-0","flg":20},"ev","str","^Where are we?","/str","/ev",{"*":".^.c-1","flg":20},"ev","str","^Why are you here?","/str","/ev",{"*":".^.c-2","flg":20},"ev","str","^See you later.","/str","/ev",{"*":".^.c-3","flg":4},{"c-0":["^ ",{"->":"name"},"\n",{"#f":5}],"c-1":["^ ",{"->":"where"},"\n",{"#f":5}],"c-2":["^ ",{"->":"why"},"\n",{"#f":5}],"c-3":["^ ",{"->":"ending"},"\n",{"#f":5}]}],{"#f":1}],"name":[["^Warrior:What's it to you, ya bag a bones?","\n","^Heldar:Heldar's my name and I'm a veteran warrior of the emerald plains!","\n","ev","str","^Emerald Plains?","/str","/ev",{"*":".^.c-0","flg":4},{"c-0":["\n","^Heldar:How do you not know of the Emerald Plains!? Those plains have been designated as a high risk zone due to hazardous magical phenomena.","\n","^Heldar:The monsters in that area have adapted to that region, making them strange and agressive.","\n","^Heldar:People like me who've grown up in such a place are better than most.","\n",{"->":"intro"},{"#f":5}]}],{"#f":1}],"where":["ev",{"CNT?":"name"},"/ev",[{"->":".^.b","c":true},{"b":["^ Heldar",{"->":"where.5"},null]}],[{"->":".^.b"},{"b":["^Warrior",{"->":"where.5"},null]}],"nop","^:I know just as much as the other two.","\n","ev",{"CNT?":"name"},"/ev",[{"->":".^.b","c":true},{"b":["^ Heldar",{"->":"where.13"},null]}],[{"->":".^.b"},{"b":["^Warrior",{"->":"where.13"},null]}],"nop","^:One moment I'm on the hunt and in the next I'm here with these two limp wrist fools.","\n",{"->":"intro"},{"#f":1}],"why":["ev",{"CNT?":"name"},"/ev",[{"->":".^.b","c":true},{"b":["^ Heldar",{"->":"why.5"},null]}],[{"->":".^.b"},{"b":["^Warrior",{"->":"why.5"},null]}],"nop","^:It's hard to say, stuff like this happening isn't unheard of.","\n","ev",{"CNT?":"name"},"/ev",[{"->":".^.b","c":true},{"b":["^ Heldar",{"->":"why.13"},null]}],[{"->":".^.b"},{"b":["^Warrior",{"->":"why.13"},null]}],"nop","^:Maybe it is simply another phenomena of the emerald plains.","\n","ev",{"CNT?":"name"},"/ev",[{"->":".^.b","c":true},{"b":["^ Heldar",{"->":"why.21"},null]}],[{"->":".^.b"},{"b":["^Warrior",{"->":"why.21"},null]}],"nop","^:That doesn't explain why the other two are here though...","\n",{"->":"intro"},{"#f":1}],"ending":["ev",{"CNT?":"name"},"/ev",[{"->":".^.b","c":true},{"b":["^ Heldar",{"->":"ending.5"},null]}],[{"->":".^.b"},{"b":["^Warrior",{"->":"ending.5"},null]}],"nop","^:So you don't know anything!? USELESS MAGI!!","\n","end",{"#f":1}],"#f":1}],"listDefs":{}}